laddu_cpu/__init__.py
laddu_cpu/laddu_cpu.cpython-313t-i386-linux-musl.so
laddu_cpu-0.14.1.dist-info/METADATA
laddu_cpu-0.14.1.dist-info/WHEEL
laddu_cpu.libs/libgcc_s-f5fcfe20.so.1
laddu_cpu-0.14.1.dist-info/RECORD
